README.txt
setup.py
webpage2html.py
test/test.py
webpage2html.egg-info/PKG-INFO
webpage2html.egg-info/SOURCES.txt
webpage2html.egg-info/dependency_links.txt
webpage2html.egg-info/entry_points.txt
webpage2html.egg-info/top_level.txt