Metadata-Version: 1.1
Name: webpage2html
Version: 0.2.0
Summary: Save/convert web pages to a single editable html file
Home-page: https://github.com/zTrix/webpage2html
Author: Wenlei Zhu
Author-email: i@ztrix.me
License: LICENSE.txt
Keywords: webpage html convert
Platform: UNKNOWN
Classifier: Development Status :: 5 - Production/Stable
Classifier: Environment :: Console
Classifier: Intended Audience :: Developers
Classifier: Operating System :: POSIX
Classifier: Operating System :: MacOS :: MacOS X
Classifier: Programming Language :: Python
Classifier: Programming Language :: Python :: 2.6
Classifier: Programming Language :: Python :: 2.7
Classifier: Topic :: Software Development
Classifier: Topic :: System
Classifier: Topic :: Terminals
Classifier: Topic :: Utilities
